estimenergy/__init__.py
estimenergy/config.py
estimenergy/const.py
estimenergy/db.py
estimenergy/devices/__init__.py
estimenergy/devices/base_device.py
estimenergy/devices/device_error.py
estimenergy/devices/device_registry.py
estimenergy/devices/glow_device.py
estimenergy/helpers.py
estimenergy/influx.py
estimenergy/log.py
estimenergy/main.py
estimenergy/models/__init__.py
estimenergy/models/config/__init__.py
estimenergy/models/config/config.py
estimenergy/models/config/dev_config.py
estimenergy/models/config/influx_config.py
estimenergy/models/config/logging_config.py
estimenergy/models/config/networking_config.py
estimenergy/models/config/sql_config.py
estimenergy/models/day.py
estimenergy/models/device_config.py
estimenergy/models/message.py
estimenergy/models/month.py
estimenergy/models/total.py
estimenergy/models/year.py
estimenergy/prometheus.py
estimenergy/routers/__init__.py
estimenergy/routers/day_router.py
estimenergy/routers/device_router.py
estimenergy/routers/month_router.py
estimenergy/routers/total_router.py
estimenergy/routers/year_router.py
estimenergy/services/__init__.py
estimenergy/services/data_service.py
estimenergy/services/influx_service.py
estimenergy/services/prediction_service.py
estimenergy/services/prometheus_service.py
estimenergy/services/sql_service.py
estimenergy-2.1.2.dist-info/LICENSE
estimenergy-2.1.2.dist-info/METADATA
estimenergy-2.1.2.dist-info/WHEEL
estimenergy-2.1.2.dist-info/entry_points.txt
estimenergy-2.1.2.dist-info/RECORD
