Metadata-Version: 2.1
Name: estimenergy
Version: 2.1.2
Summary: Estimate Energy Consumption
Home-page: https://github.com/EuleMitKeule/EstimEnergy
License: MIT
Author: Lennard Beers
Author-email: l.beers@outlook.de
Requires-Python: >=3.10,<4.0
Classifier: License :: OSI Approved :: MIT License
Classifier: Programming Language :: Python :: 3
Classifier: Programming Language :: Python :: 3.10
Classifier: Programming Language :: Python :: 3.11
Requires-Dist: PyYAML (>=6.0,<6.1)
Requires-Dist: aioesphomeapi (==13.7.2)
Requires-Dist: fastapi (>=0.92.0,<0.93.0)
Requires-Dist: fastapi-crudrouter (>=0.8.6,<0.9.0)
Requires-Dist: influxdb-client[async] (>=1.36.1,<2.0.0)
Requires-Dist: prometheus-fastapi-instrumentator (>=5.10.0,<5.11.0)
Requires-Dist: prometheus_client (>=0.16.0,<0.17.0)
Requires-Dist: psycopg2-binary (>=2.9.6,<3.0.0)
Requires-Dist: python-dotenv (>=0.21.1,<0.22.0)
Requires-Dist: requests (>=2.28.2,<2.29.0)
Requires-Dist: sqlmodel (>=0.0.8,<0.0.9)
Requires-Dist: types-pyyaml (>=6.0.12.9,<7.0.0.0)
Requires-Dist: types-requests (>=2.28.11.17,<3.0.0.0)
Requires-Dist: uvicorn[standard] (>=0.20.0,<0.21.0)
Project-URL: Repository, https://github.com/EuleMitKeule/EstimEnergy
